gym_ignition/__init__.py
gym_ignition/base/__init__.py
gym_ignition/base/runtime.py
gym_ignition/base/task.py
gym_ignition/context/__init__.py
gym_ignition/context/gazebo/__init__.py
gym_ignition/context/gazebo/controllers.py
gym_ignition/context/gazebo/plugin.py
gym_ignition/randomizers/__init__.py
gym_ignition/randomizers/abc.py
gym_ignition/randomizers/gazebo_env_randomizer.py
gym_ignition/randomizers/model/__init__.py
gym_ignition/randomizers/model/sdf.py
gym_ignition/randomizers/physics/__init__.py
gym_ignition/randomizers/physics/dart.py
gym_ignition/rbd/__init__.py
gym_ignition/rbd/conversions.py
gym_ignition/rbd/utils.py
gym_ignition/rbd/idyntree/__init__.py
gym_ignition/rbd/idyntree/helpers.py
gym_ignition/rbd/idyntree/inverse_kinematics_nlp.py
gym_ignition/rbd/idyntree/kindyncomputations.py
gym_ignition/rbd/idyntree/numpy.py
gym_ignition/runtimes/__init__.py
gym_ignition/runtimes/gazebo_runtime.py
gym_ignition/runtimes/realtime_runtime.py
gym_ignition/scenario/__init__.py
gym_ignition/scenario/model_with_file.py
gym_ignition/scenario/model_wrapper.py
gym_ignition/utils/__init__.py
gym_ignition/utils/logger.py
gym_ignition/utils/math.py
gym_ignition/utils/misc.py
gym_ignition/utils/resource_finder.py
gym_ignition/utils/scenario.py
gym_ignition/utils/typing.py
gym_ignition_environments/__init__.py
gym_ignition_environments/models/__init__.py
gym_ignition_environments/models/cartpole.py
gym_ignition_environments/models/icub.py
gym_ignition_environments/models/panda.py
gym_ignition_environments/models/pendulum.py
gym_ignition_environments/randomizers/__init__.py
gym_ignition_environments/randomizers/cartpole.py
gym_ignition_environments/randomizers/cartpole_no_rand.py
gym_ignition_environments/tasks/__init__.py
gym_ignition_environments/tasks/cartpole_continuous_balancing.py
gym_ignition_environments/tasks/cartpole_continuous_swingup.py
gym_ignition_environments/tasks/cartpole_discrete_balancing.py
gym_ignition_environments/tasks/pendulum_swingup.py
gym_ignition-1.3.1.dist-info/LICENSE
gym_ignition-1.3.1.dist-info/METADATA
gym_ignition-1.3.1.dist-info/WHEEL
gym_ignition-1.3.1.dist-info/top_level.txt
gym_ignition-1.3.1.dist-info/RECORD
