Metadata-Version: 2.1
Name: gym-ignition
Version: 1.3.1
Summary: A toolkit for developing OpenAI Gym environments simulated with Ignition Gazebo.
Home-page: https://github.com/robotology/gym-ignition
Author: Diego Ferigo
Author-email: dgferigo@gmail.com
License: LGPL
Project-URL: Changelog, https://github.com/robotology/gym-ignition/releases
Project-URL: Tracker, https://github.com/robotology/gym-ignition/issues
Project-URL: Documentation, https://robotology.github.io/gym-ignition
Project-URL: Source, https://github.com/robotology/gym-ignition
Keywords: openai,gym,reinforcement learning,rl,environment,gazebo,robotics,ignition,humanoid,panda,icub,urdf,sdf
Platform: any
Classifier: Development Status :: 5 - Production/Stable
Classifier: Operating System :: POSIX :: Linux
Classifier: Topic :: Games/Entertainment :: Simulation
Classifier: Topic :: Scientific/Engineering :: Artificial Intelligence
Classifier: Topic :: Scientific/Engineering :: Physics
Classifier: Topic :: Software Development
Classifier: Framework :: Robot Framework
Classifier: Intended Audience :: Developers
Classifier: Intended Audience :: Science/Research
Classifier: Programming Language :: Python :: 3.8
Classifier: Programming Language :: Python :: 3.9
Classifier: Programming Language :: Python :: 3 :: Only
Classifier: Programming Language :: Python :: Implementation :: CPython
Classifier: License :: OSI Approved :: GNU Lesser General Public License v2 or later (LGPLv2+)
Requires-Python: >=3.8
License-File: LICENSE
Requires-Dist: scenario (~=1.3.1.pre)
Requires-Dist: gym (>=0.13.1)
Requires-Dist: numpy
Requires-Dist: scipy
Requires-Dist: gym-ignition-models
Requires-Dist: lxml
Requires-Dist: idyntree
Provides-Extra: all
Requires-Dist: pytest ; extra == 'all'
Requires-Dist: pytest-xvfb ; extra == 'all'
Requires-Dist: pytest-icdiff ; extra == 'all'
Requires-Dist: sphinx ; extra == 'all'
Requires-Dist: sphinx-book-theme ; extra == 'all'
Requires-Dist: sphinx-autodoc-typehints ; extra == 'all'
Requires-Dist: sphinx-fontawesome ; extra == 'all'
Requires-Dist: sphinx-multiversion ; extra == 'all'
Requires-Dist: sphinx-tabs ; extra == 'all'
Requires-Dist: breathe ; extra == 'all'
Provides-Extra: testing
Requires-Dist: pytest ; extra == 'testing'
Requires-Dist: pytest-xvfb ; extra == 'testing'
Requires-Dist: pytest-icdiff ; extra == 'testing'
Provides-Extra: website
Requires-Dist: sphinx ; extra == 'website'
Requires-Dist: sphinx-book-theme ; extra == 'website'
Requires-Dist: sphinx-autodoc-typehints ; extra == 'website'
Requires-Dist: sphinx-fontawesome ; extra == 'website'
Requires-Dist: sphinx-multiversion ; extra == 'website'
Requires-Dist: sphinx-tabs ; extra == 'website'
Requires-Dist: breathe ; extra == 'website'
